setup.py
cyclops/__init__.py
cyclops/app.py
cyclops/cache.py
cyclops/config.py
cyclops/count.py
cyclops/db.py
cyclops/init.py
cyclops/projects.py
cyclops/server.py
cyclops/storage.py
cyclops/tasks.py
cyclops.egg-info/PKG-INFO
cyclops.egg-info/SOURCES.txt
cyclops.egg-info/dependency_links.txt
cyclops.egg-info/entry_points.txt
cyclops.egg-info/not-zip-safe
cyclops.egg-info/requires.txt
cyclops.egg-info/top_level.txt
cyclops/handlers/__init__.py
cyclops/handlers/base.py
cyclops/handlers/healthcheck.py
cyclops/handlers/router.py
tests/__init__.py
tests/helpers.py
tests/test_app.py
tests/test_cache.py
tests/test_conf.py
tests/test_server.py
tests/test_storage.py
tests/handlers/__init__.py
tests/handlers/test_router.py