Metadata-Version: 1.1
Name: cyclops
Version: 1.1.1
Summary: cyclops is a high-performance gateway for sentry.
Home-page: https://github.com/heynemann/cyclops
Author: Bernardo Heynemann
Author-email: heynemann@gmail.com
License: MIT
Keywords: bug monitoring tornado
Platform: UNKNOWN
Classifier: Development Status :: 3 - Alpha
Classifier: Intended Audience :: Developers
Classifier: License :: OSI Approved :: MIT License
Classifier: Natural Language :: English
Classifier: Operating System :: MacOS
Classifier: Operating System :: POSIX :: Linux
Classifier: Programming Language :: Python :: 2.6
Classifier: Programming Language :: Python :: 2.7
